rust_magic/__init__.py
rust_magic/a.py
rust_magic/b.py
rust_magic/c.py
rust_magic/rust_magic.py
rust_magic-0.3.3.dist-info/LICENSE
rust_magic-0.3.3.dist-info/METADATA
rust_magic-0.3.3.dist-info/WHEEL
rust_magic-0.3.3.dist-info/top_level.txt
rust_magic-0.3.3.dist-info/RECORD
