Metadata-Version: 2.1
Name: rust-magic
Version: 0.3.3
Summary: Lightweight Rust integration in Jupyter notebook
Home-page: https://github.com/axil/rust-magic
Author: Lev Maximov
Author-email: lev.maximov@gmail.com
License: MIT License
Keywords: rust,jupyter,notebook,magic
Platform: UNKNOWN
Classifier: Programming Language :: Python :: 3
Classifier: License :: OSI Approved :: MIT License
Classifier: Operating System :: OS Independent
